asSQL/__init__.py
asSQL/asSQL.py
asSQL-2023.1.3.dist-info/LICENSE
asSQL-2023.1.3.dist-info/METADATA
asSQL-2023.1.3.dist-info/WHEEL
asSQL-2023.1.3.dist-info/top_level.txt
asSQL-2023.1.3.dist-info/RECORD
