Metadata-Version: 2.1
Name: asSQL
Version: 2023.1.3
Summary: a simple database based on sqlite3
Home-page: 
Author: ReBack
Author-email: 
Project-URL: Bug Tracker, https://github.com/pypa/sampleproject/issues
Keywords: ai,sql,database
Classifier: Development Status :: 1 - Planning
Classifier: Intended Audience :: Developers
Classifier: Programming Language :: Python :: 3
License-File: LICENSE
Requires-Dist: requests
